MANIFEST.in
readme.md
setup.py
mqspeak/__init__.py
mqspeak/__main__.py
mqspeak/args.py
mqspeak/channel.py
mqspeak/collecting.py
mqspeak/config.py
mqspeak/data.py
mqspeak/sending.py
mqspeak/system.py
mqspeak/updating.py
mqspeak.egg-info/PKG-INFO
mqspeak.egg-info/SOURCES.txt
mqspeak.egg-info/dependency_links.txt
mqspeak.egg-info/entry_points.txt
mqspeak.egg-info/requires.txt
mqspeak.egg-info/top_level.txt